mcp_gitlab_server/__init__.py
mcp_gitlab_server-0.0.4.dist-info/METADATA
mcp_gitlab_server-0.0.4.dist-info/WHEEL
mcp_gitlab_server-0.0.4.dist-info/entry_points.txt
mcp_gitlab_server-0.0.4.dist-info/licenses/LICENSE
mcp_gitlab_server-0.0.4.dist-info/RECORD
