Metadata-Version: 2.4
Name: mcp-gitlab-server
Version: 0.0.4
Summary: GitLab MCP server
Author-email: Daniel Pastrana <daniel@example.com>
License: MIT
License-File: LICENSE
Keywords: gitlab,mcp
Classifier: Development Status :: 3 - Alpha
Classifier: License :: OSI Approved :: MIT License
Classifier: Programming Language :: Python :: 3.13
Requires-Python: >=3.13
Requires-Dist: mcp<2.0.0,>=1.9.0
Requires-Dist: python-gitlab<5.0.0,>=4.0.0
Provides-Extra: dev
Requires-Dist: ipdb; extra == 'dev'
Requires-Dist: ipykernel; extra == 'dev'
Requires-Dist: ipython; extra == 'dev'
Requires-Dist: mcp[cli]; extra == 'dev'
Provides-Extra: linting
Requires-Dist: mypy; extra == 'linting'
Requires-Dist: ruff; extra == 'linting'
Requires-Dist: types-requests; extra == 'linting'
